clausewitz/__init__.py
clausewitz/__version__.py
clausewitz/utils.py
clausewitz/antlr/ClausewitzLexer.py
clausewitz/antlr/ClausewitzListener.py
clausewitz/antlr/ClausewitzParser.py
clausewitz/antlr/ClausewitzVisitor.py
clausewitz/antlr/__init__.py
clausewitz/division_builder/__init__.py
clausewitz/division_builder/division_builder.py
clausewitz/division_builder/technologies.py
clausewitz/hoi4_parsing/__init__.py
clausewitz/hoi4_parsing/parse_def.py
clausewitz/land_warfare/__init__.py
clausewitz/land_warfare/land_warfare_calc.py
clausewitz/parser/__init__.py
clausewitz/parser/parser.py
PyClausewitz-0.0.1.dist-info/LICENSE
PyClausewitz-0.0.1.dist-info/METADATA
PyClausewitz-0.0.1.dist-info/WHEEL
PyClausewitz-0.0.1.dist-info/top_level.txt
PyClausewitz-0.0.1.dist-info/RECORD
