Metadata-Version: 2.1
Name: PyClausewitz
Version: 0.0.1
Summary: PyClausewitz is an Open Source Tool for Clausewitz.
Home-page: https://github.com/LokiSharp/PyClausewitz
Author: LokiSharp
Author-email: loki.sharp@gmail.com
License: AGPLv3
Platform: UNKNOWN
Classifier: License :: OSI Approved :: GNU Affero General Public License v3
Classifier: Programming Language :: Python
Classifier: Programming Language :: Python :: 3
Classifier: Programming Language :: Python :: 3.6
Classifier: Programming Language :: Python :: Implementation :: CPython
Classifier: Programming Language :: Python :: Implementation :: PyPy
Requires-Python: >=3.6.0
Requires-Dist: pyparsing
Requires-Dist: tqdm
Requires-Dist: scipy
Requires-Dist: antlr4-python3-runtime
Provides-Extra: dev
Requires-Dist: mypy ; extra == 'dev'
Requires-Dist: pytest ; extra == 'dev'
Requires-Dist: coveralls ; extra == 'dev'
Requires-Dist: twine ; extra == 'dev'
